setup.py
spread/__init__.py
spread/main.py
spread/porter.py
spread.egg-info/PKG-INFO
spread.egg-info/SOURCES.txt
spread.egg-info/dependency_links.txt
spread.egg-info/top_level.txt