Metadata-Version: 1.0
Name: spread
Version: 1.1.20
Summary: CSV Spreadsheet library
Home-page: http://github.com/vbuterin/spread
Author: Vitalik Buterin
Author-email: v@buterin.com
License: UNKNOWN
Platform: UNKNOWN
